{
  "_comment": "钨钢产品同义词表 + 类别区分词，随产品库一起加载。可按需扩展。",

  "synonyms": {
    "button":       ["spherical", "insert", "gear", "inserts"],
    "buttons":      ["spherical", "insert", "gear", "inserts"],
    "insert":       ["spherical", "button", "gear", "inserts"],
    "inserts":      ["spherical", "button", "gear"],
    "pick":         ["teeth", "tooth", "tunneling", "shearer", "roadheader"],
    "picks":        ["teeth", "tooth", "tunneling", "shearer"],
    "tip":          ["teeth", "tooth", "carbide", "milling", "coal"],
    "tips":         ["teeth", "tooth", "carbide", "milling", "coal"],
    "cutter":       ["teeth", "tooth", "bit", "milling", "strip"],
    "cutters":      ["teeth", "tooth", "bit", "milling"],
    "rod":          ["bar", "blank", "blanks", "round", "raw"],
    "rods":         ["bar", "blank", "blanks", "round", "raw"],
    "bar":          ["rod", "blank", "strip", "flat", "raw"],
    "bars":         ["rod", "blank", "strip", "flat", "raw"],
    "strip":        ["bar", "flat", "blade", "plate"],
    "strips":       ["bar", "flat", "blade", "plate"],
    "blank":        ["rod", "bar", "raw", "material"],
    "blanks":       ["rod", "bar", "raw", "material"],
    "dth":          ["spherical", "drilling", "down", "hole", "button"],
    "tbm":          ["shield", "tunneling", "engineering", "cutterhead"],
    "shearer":      ["teeth", "tooth", "coal", "pick", "tunneling"],
    "roadheader":   ["teeth", "tooth", "tunneling", "pick", "mining"],
    "drilling":     ["dth", "bit", "spherical", "insert", "button"],
    "tungsten":     ["carbide", "wc", "cemented"],
    "carbide":      ["tungsten", "wc", "cemented", "tc"],
    "cemented":     ["carbide", "tungsten", "wc"],
    "wc":           ["carbide", "tungsten", "cemented"],
    "mushroom":     ["tooth", "teeth", "coal", "mushroom"],
    "exotic":       ["cemented", "special", "alloy", "grade"],
    "flat":         ["strip", "bar", "blade", "plate"],
    "milling":      ["cutter", "tip", "insert", "endmill"],
    "coal":         ["shearer", "mining", "tooth", "pick", "mushroom"],
    "mining":       ["pick", "teeth", "tooth", "drill", "shearer", "coal"],
    "raw":          ["material", "blank", "bar", "rod", "unground"],
    "material":     ["raw", "blank", "bar", "rod"],
    "grade":        ["spec", "alloy", "type", "quality"],
    "alloy":        ["cemented", "carbide", "grade", "exotic"]
  },

  "category_hints": {
    "Engineering Shield Teeth":       ["shield", "tbm", "cutterhead", "cutter", "head", "tunnel", "boring"],
    "Spherical Gear Inserts":         ["dth", "spherical", "button", "insert", "drilling", "down", "hole", "percussive", "oil"],
    "Carbide Tunneling Teeth":        ["tunneling", "roadheader", "shearer", "pick", "mining", "conical"],
    "Coal Tooth Carbide Tips":        ["coal", "shearer", "mushroom", "mining", "pick", "tooth"],
    "Carbide Mushroom Tooth":         ["mushroom", "coal", "shearer", "mining"],
    "Cutter Bits / Rotary Drilling Bits": ["rotary", "bit", "drilling", "cutter", "roller"],
    "Milling Cutter Carbide Tips":    ["milling", "cutter", "tip", "endmill", "insert", "cnc", "turning"],
    "Tungsten Carbide Rod Blanks":    ["rod", "blank", "round", "bar", "unground", "ground"],
    "Carbide Rod Raw Material Bars":  ["rod", "bar", "raw", "material", "blank", "extrusion"],
    "Tungsten Carbide Strips":        ["strip", "flat", "bar", "blade", "plate", "rectangular"],
    "Exotic Cemented Carbide Alloy":  ["exotic", "special", "grade", "alloy", "custom", "nonstandard"]
  }
}
